Janitor/Janitor.py
Janitor/__init__.py
janitor_cubix-0.0.3.dist-info/licenses/LICENSE
janitor_cubix-0.0.3.dist-info/METADATA
janitor_cubix-0.0.3.dist-info/WHEEL
janitor_cubix-0.0.3.dist-info/top_level.txt
janitor_cubix-0.0.3.dist-info/RECORD
