Metadata-Version: 2.4
Name: janitor-cubix
Version: 0.0.3
Summary: Janitor Library
Author: Cubix523
License: MIT
Requires-Python: >=3.7
License-File: LICENSE
Provides-Extra: dev
Requires-Dist: pytest; extra == "dev"
Dynamic: author
Dynamic: description
Dynamic: description-content-type
Dynamic: license
Dynamic: license-file
Dynamic: provides-extra
Dynamic: requires-python
Dynamic: summary
